{
    "name": "Global Information",
    "numberOfRequests": {
        "total": 4800,
        "ok": 2282,
        "ko": 2518
    },
    "minResponseTime": {
        "total": 6,
        "ok": 9,
        "ko": 6
    },
    "maxResponseTime": {
        "total": 22749,
        "ok": 22749,
        "ko": 10995
    },
    "meanResponseTime": {
        "total": 3060,
        "ok": 4046,
        "ko": 2167
    },
    "standardDeviation": {
        "total": 3297,
        "ok": 4163,
        "ko": 1828
    },
    "percentiles1": {
        "total": 2007,
        "ok": 2587,
        "ko": 1597
    },
    "percentiles2": {
        "total": 4064,
        "ok": 6102,
        "ko": 3090
    },
    "percentiles3": {
        "total": 10476,
        "ok": 12738,
        "ko": 5784
    },
    "percentiles4": {
        "total": 14977,
        "ok": 17211,
        "ko": 7846
    },
    "group1": {
        "name": "t < 800 ms",
        "count": 530,
        "percentage": 11
    },
    "group2": {
        "name": "800 ms < t < 1200 ms",
        "count": 102,
        "percentage": 2
    },
    "group3": {
        "name": "t > 1200 ms",
        "count": 1650,
        "percentage": 34
    },
    "group4": {
        "name": "failed",
        "count": 2518,
        "percentage": 52
    },
    "meanNumberOfRequestsPerSecond": {
        "total": 54.54545454545455,
        "ok": 25.931818181818183,
        "ko": 28.613636363636363
    }
}